CHANGELOG.txt
LICENCE.txt
MANIFEST.in
README.txt
setup.py
voxyl_api/__init__.py
voxyl_api.egg-info/PKG-INFO
voxyl_api.egg-info/SOURCES.txt
voxyl_api.egg-info/dependency_links.txt
voxyl_api.egg-info/requires.txt
voxyl_api.egg-info/top_level.txt