Metadata-Version: 2.1
Name: voxyl-api
Version: 1.0
Summary: An easy wrapper for https://api.voxyl.net/ written in Python
Home-page: UNKNOWN
Author: Davey Adams
Author-email: davey.adams.three@gmail.com
License: MIT
Keywords: voxyl api
Platform: UNKNOWN
Classifier: Development Status :: 5 - Production/Stable
Classifier: Intended Audience :: Education
Classifier: Operating System :: Microsoft :: Windows :: Windows 10
Classifier: License :: OSI Approved :: MIT License
Classifier: Programming Language :: Python :: 3
License-File: LICENCE.txt
